anonchat/__init__.py
anonchat/client.py
anonchat-0.0.3.dist-info/LICENSE
anonchat-0.0.3.dist-info/METADATA
anonchat-0.0.3.dist-info/WHEEL
anonchat-0.0.3.dist-info/top_level.txt
anonchat-0.0.3.dist-info/RECORD
