Metadata-Version: 2.1
Name: anonchat
Version: 0.0.3
Summary: Package for interacting with anonchat servers
Home-page: https://github.com/anonchat-org/anonchat-api.py
Author: KrutosX
Author-email: krutosviprus@gmail.com
License: UNKNOWN
Project-URL: Bug Tracker, https://github.com/anonchat-org/anonchat-api.py/issues
Platform: UNKNOWN
Classifier: Programming Language :: Python :: 3
Classifier: License :: OSI Approved :: MIT License
Classifier: Operating System :: OS Independent
Requires-Python: >=3.6
License-File: LICENSE
